bcruds/__init__.py
bcruds/main.py
bcruds-0.0.1.dist-info/LICENSE.txt
bcruds-0.0.1.dist-info/METADATA
bcruds-0.0.1.dist-info/WHEEL
bcruds-0.0.1.dist-info/top_level.txt
bcruds-0.0.1.dist-info/RECORD
